{"__symbolic":"module","version":1,"metadata":{"ScaleLegend":{"__symbolic":"class","decorators":[{"__symbolic":"call","expression":{"__symbolic":"reference","module":"@angular/core","name":"Component"},"arguments":[{"selector":"scale-legend","template":"\n    <div\n      class=\"scale-legend\"\n      [style.width]=\"width + 'px'\">\n      <div [style.height]=\"(height - 70) + 'px'\">\n\n        <div class=\"scale-legend-label\">\n          <span>{{ valueRange[0].toFixed() }}</span>\n        </div>\n\n        <div class=\"scale-legend-wrap\"\n          [style.background]=\"gradient\">\n        </div>\n\n        <div class=\"scale-legend-label\">\n          <span>{{ valueRange[1].toFixed() }}</span>\n        </div>\n      </div>\n    </div>\n  "}]}],"members":{"valueRange":[{"__symbolic":"property","decorators":[{"__symbolic":"call","expression":{"__symbolic":"reference","module":"@angular/core","name":"Input"}}]}],"colors":[{"__symbolic":"property","decorators":[{"__symbolic":"call","expression":{"__symbolic":"reference","module":"@angular/core","name":"Input"}}]}],"height":[{"__symbolic":"property","decorators":[{"__symbolic":"call","expression":{"__symbolic":"reference","module":"@angular/core","name":"Input"}}]}],"width":[{"__symbolic":"property","decorators":[{"__symbolic":"call","expression":{"__symbolic":"reference","module":"@angular/core","name":"Input"}}]}],"__ctor__":[{"__symbolic":"constructor","parameters":[{"__symbolic":"reference","module":"@angular/platform-browser","name":"DomSanitizer"}]}],"ngOnChanges":[{"__symbolic":"method"}],"gradientString":[{"__symbolic":"method"}]}}}}